foliant/preprocessors/macros.py
foliantcontrib.macros-1.0.5.dist-info/LICENSE
foliantcontrib.macros-1.0.5.dist-info/METADATA
foliantcontrib.macros-1.0.5.dist-info/WHEEL
foliantcontrib.macros-1.0.5.dist-info/top_level.txt
foliantcontrib.macros-1.0.5.dist-info/RECORD
